openmt/__init__.py
openmt/config/__init__.py
openmt/config/config.py
openmt/config/config_test.py
openmt/detect/__init__.py
openmt/detect/config.py
openmt/detect/config_test.py
openmt/detect/predict.py
openmt/detect/predict_test.py
openmt/detect/train.py
openmt/detect/train_test.py
openmt/unittest/__init__.py
openmt/unittest/util.py
openmt/util/__init__.py
openmt/util/defaults.py
openmt/util/defaults_test.py
systm/__init__.py
systm/config/__init__.py
systm/config/config.py
systm/config/config_test.py
systm/detect/__init__.py
systm/detect/config.py
systm/detect/predict.py
systm/detect/predict_test.py
systm/detect/train.py
systm/detect/train_test.py
systm/unittest/__init__.py
systm/unittest/util.py
systm/util/__init__.py
systm/util/defaults.py
openmt-0.0.dist-info/LICENSE
openmt-0.0.dist-info/METADATA
openmt-0.0.dist-info/WHEEL
openmt-0.0.dist-info/top_level.txt
openmt-0.0.dist-info/RECORD
